langchain_netmind/__init__.py
langchain_netmind/chat_models.py
langchain_netmind/embeddings.py
langchain_netmind-0.1.0.dist-info/LICENSE
langchain_netmind-0.1.0.dist-info/METADATA
langchain_netmind-0.1.0.dist-info/WHEEL
langchain_netmind-0.1.0.dist-info/RECORD
